jupyter_slurm_http_provisioner/__init__.py
jupyter_slurm_http_provisioner/http_provisioner.py
jupyter_slurm_http_provisioner-0.2.1.dist-info/METADATA
jupyter_slurm_http_provisioner-0.2.1.dist-info/WHEEL
jupyter_slurm_http_provisioner-0.2.1.dist-info/entry_points.txt
jupyter_slurm_http_provisioner-0.2.1.dist-info/licenses/LICENSE
jupyter_slurm_http_provisioner-0.2.1.dist-info/RECORD
