Metadata-Version: 2.4
Name: jupyter_slurm_http_provisioner
Version: 0.2.1
Summary: Start a remote Kernel via http in a slurm job, and connect to it with ssh tunnels
Project-URL: Homepage, https://github.com/Ninichus/jupyter_slurm_http_provisioner
Project-URL: Issues, https://github.com/Ninichus/jupyter_slurm_http_provisioner/issues
Author-email: Arthur Conrozier <arthur.conrozier@hotmail.fr>
License-Expression: MIT
License-File: LICENSE
Requires-Dist: httpx
Requires-Dist: jupyter-client>=7.0.0
